Metadata-Version: 2.1
Name: flask-project-builder-python
Version: 0.0.1
Summary: Projeto para facilitar a criação de projetos Flask
Author: Carlos Eduardo Ferreia Fernandes
Author-email: carloseduardo082005@icloud.com
License: MIT License
Keywords: flask project builder
License-File: LICENCE
